home/ubuntu/.yac/config/websites_config.ini
yac/__init__.py
yac/main.py
yac/utils/__init__.py
yac/utils/logger.py
yac/utils/vparser.py
yachecker-1.0.2.dist-info/METADATA
yachecker-1.0.2.dist-info/WHEEL
yachecker-1.0.2.dist-info/entry_points.txt
yachecker-1.0.2.dist-info/top_level.txt
yachecker-1.0.2.dist-info/RECORD
