Metadata-Version: 2.1
Name: yachecker
Version: 1.0.2
Summary: YAC: Yes Another Checker
Home-page: https://github.com/hithmast/YAC.git
Author: Ali Emara
Author-email: ali.emara175@gmail.com
License: UNKNOWN
Platform: UNKNOWN
Classifier: Programming Language :: Python :: 3
Classifier: License :: OSI Approved :: MIT License
Classifier: Operating System :: OS Independent
Requires-Python: >=3.6
Requires-Dist: argparse
Requires-Dist: requests
Requires-Dist: urllib3
